solentware_bind/__init__.py
solentware_bind/gui/__init__.py
solentware_bind/gui/bindings.py
solentware_bind/gui/exceptionhandler.py
solentware_bind-1.0.2.dist-info/LICENCE
solentware_bind-1.0.2.dist-info/METADATA
solentware_bind-1.0.2.dist-info/WHEEL
solentware_bind-1.0.2.dist-info/top_level.txt
solentware_bind-1.0.2.dist-info/RECORD
