Metadata-Version: 2.1
Name: solentware-bind
Version: 1.0.2
Summary: Bind and exception handling for tkinter callbacks.
Author-email: Roger Marsh <roger.marsh@solentware.co.uk>
License: Licence for solentware_bind package
Project-URL: Homepage, http://www.solentware.co.uk
Project-URL: Repository, https://github.com/RogerMarsh/solentware-bind.git
Project-URL: Bug Tracker, https://github.com/RogerMarsh/solentware-bind/issues
Classifier: License :: OSI Approved :: BSD License
Classifier: Programming Language :: Python :: 3.9
Classifier: Programming Language :: Python :: 3.10
Classifier: Programming Language :: Python :: 3.11
Classifier: Programming Language :: Python :: 3.12
Classifier: Operating System :: OS Independent
Classifier: Topic :: Software Development
Classifier: Intended Audience :: Developers
Classifier: Development Status :: 3 - Alpha
License-File: LICENCE
